os_service_types/__init__.py
os_service_types/exc.py
os_service_types/service_types.py
os_service_types/types.py
os_service_types/data/__init__.py
os_service_types/data/service-types.json
os_service_types/tests/__init__.py
os_service_types/tests/base.py
os_service_types/tests/test_builtin.py
os_service_types/tests/test_data.py
os_service_types/tests/test_match.py
os_service_types/tests/test_misc.py
os_service_types/tests/test_remote.py
os_service_types/tests/test_singleton.py
os_service_types/tests/test_warn.py
os_service_types-1.8.0.dist-info/AUTHORS
os_service_types-1.8.0.dist-info/LICENSE
os_service_types-1.8.0.dist-info/METADATA
os_service_types-1.8.0.dist-info/WHEEL
os_service_types-1.8.0.dist-info/pbr.json
os_service_types-1.8.0.dist-info/top_level.txt
os_service_types-1.8.0.dist-info/RECORD
