Metadata-Version: 2.1
Name: os-service-types
Version: 1.8.0
Summary: Python library for consuming OpenStack sevice-types-authority data
Author-email: OpenStack <openstack-discuss@lists.openstack.org>
License: Apache-2.0
Project-URL: Homepage, https://docs.openstack.org/os-service-types/
Project-URL: Repository, https://opendev.org/openstack/os-service-types/
Classifier: Environment :: OpenStack
Classifier: Intended Audience :: Developers
Classifier: License :: OSI Approved :: Apache Software License
Classifier: Operating System :: POSIX :: Linux
Classifier: Programming Language :: Python
Classifier: Programming Language :: Python :: 3
Classifier: Programming Language :: Python :: 3.10
Classifier: Programming Language :: Python :: 3.11
Classifier: Programming Language :: Python :: 3.12
Classifier: Programming Language :: Python :: 3.13
Requires-Python: >=3.10
License-File: LICENSE
Requires-Dist: pbr!=2.1.0,>=2.0.0
